pibot/__init__.py
pibot/pibot.py
pibot/progeo.py
pibot/test.py
jderbobot_pibot_sim-0.0.1.dist-info/METADATA
jderbobot_pibot_sim-0.0.1.dist-info/WHEEL
jderbobot_pibot_sim-0.0.1.dist-info/top_level.txt
jderbobot_pibot_sim-0.0.1.dist-info/RECORD
