Metadata-Version: 2.1
Name: jderbobot-pibot-sim
Version: 0.0.1
Summary: Drivers for simulated PiBot from JdeRobot
Home-page: https://github.com/jderobot/base.git
Author: Francisco Perez
Author-email: f.perez475@gmail.com
License: UNKNOWN
Project-URL: Bug Reports, https://makers.kibotics.org
Project-URL: Forum, https://makers.kibotics.org
Project-URL: Web, https://jderobot.org
Project-URL: Source, https://github.com/jderobot-hub/kibotics-drivers.git
Platform: UNKNOWN
Classifier: Development Status :: 3 - Alpha
Classifier: Intended Audience :: Education
Classifier: Intended Audience :: Developers
Classifier: Topic :: Software Development :: Build Tools
Classifier: Topic :: Education
Classifier: License :: OSI Approved :: GNU General Public License v3 (GPLv3)
Classifier: Programming Language :: Python :: 2.7
Classifier: Programming Language :: Python :: 3.5
Requires-Dist: opencv-python
Requires-Dist: numpy
Requires-Dist: jderobot-config
Requires-Dist: jderobot-interfaces-python
